{
  "invalid": [
    "http://dbpedia.org/ontology/capacity"
  ], 
  "labelling": {
    "property": {
      "avg": [
        [
          "populationDensity", 
          0.0869
        ], 
        [
          "populationTotal", 
          0.0901
        ], 
        [
          "elevation", 
          0.0904
        ]
      ], 
      "maj": [
        [
          "populationTotal", 
          8.0
        ], 
        [
          "populationDensity", 
          1.0
        ], 
        [
          "elevation", 
          1.0
        ]
      ]
    }, 
    "type": {
      "avg": [
        [
          "http://dbpedia.org/ontology/PopulatedPlace (populationDensity)", 
          0.0869
        ], 
        [
          "http://dbpedia.org/ontology/Country (populationDensity)", 
          0.0869
        ], 
        [
          "http://dbpedia.org/ontology/Place (populationDensity)", 
          0.0869
        ], 
        [
          "http://dbpedia.org/ontology/Place (populationTotal)", 
          0.0888
        ], 
        [
          "http://dbpedia.org/ontology/Settlement (populationTotal)", 
          0.0888
        ], 
        [
          "http://dbpedia.org/ontology/PopulatedPlace (populationTotal)", 
          0.0888
        ], 
        [
          "http://dbpedia.org/ontology/Village (populationTotal)", 
          0.0895
        ], 
        [
          "http://dbpedia.org/ontology/PopulatedPlace (elevation)", 
          0.0904
        ], 
        [
          "http://dbpedia.org/ontology/Settlement (elevation)", 
          0.0904
        ], 
        [
          "http://dbpedia.org/ontology/Place (elevation)", 
          0.0904
        ], 
        [
          "http://dbpedia.org/ontology/Town (elevation)", 
          0.0904
        ], 
        [
          "http://dbpedia.org/ontology/Location (populationTotal)", 
          0.0943
        ]
      ], 
      "maj": [
        [
          "http://dbpedia.org/ontology/Village (populationTotal)", 
          18.0
        ], 
        [
          "http://dbpedia.org/ontology/Place (populationTotal)", 
          6.0
        ], 
        [
          "http://dbpedia.org/ontology/Settlement (populationTotal)", 
          6.0
        ], 
        [
          "http://dbpedia.org/ontology/PopulatedPlace (populationTotal)", 
          6.0
        ], 
        [
          "http://dbpedia.org/ontology/Location (populationTotal)", 
          5.0
        ], 
        [
          "http://dbpedia.org/ontology/Town (elevation)", 
          2.0
        ], 
        [
          "http://dbpedia.org/ontology/PopulatedPlace (populationDensity)", 
          1.0
        ], 
        [
          "http://dbpedia.org/ontology/PopulatedPlace (elevation)", 
          1.0
        ], 
        [
          "http://dbpedia.org/ontology/Settlement (elevation)", 
          1.0
        ], 
        [
          "http://dbpedia.org/ontology/Place (elevation)", 
          1.0
        ], 
        [
          "http://dbpedia.org/ontology/Country (populationDensity)", 
          1.0
        ], 
        [
          "http://dbpedia.org/ontology/Place (populationDensity)", 
          1.0
        ]
      ]
    }
  }, 
  "neighbours": [
    [
      "Village[populationTotal]>(isPartOf|Kerman_Province)", 
      0.0824
    ], 
    [
      "Village[populationTotal]>(isPartOf|South_Khorasan_Province)", 
      0.0828
    ], 
    [
      "Country[populationDensity]", 
      0.0869
    ], 
    [
      "Village[populationTotal]>(isPartOf|Mazandaran_Province)>(isPartOf|Ramsar_County)>(22-rdf-syntax-ns#type|_Feature)", 
      0.088
    ], 
    [
      "Town[elevation]>(isPartOf|Massachusetts)", 
      0.0904
    ], 
    [
      "Village[populationTotal]>(isPartOf|Kerman_Province)>(isPartOf|Central_District_(Shahr-e_Babak_County))>(22-rdf-syntax-ns#type|_Feature)", 
      0.0908
    ], 
    [
      "Location[populationTotal]>(isPartOf|Kerman_Province)", 
      0.0928
    ], 
    [
      "Village[populationTotal]>(isPartOf|Hormozgan_Province)>(isPartOf|Central_District_(Hajjiabad_County))", 
      0.0938
    ], 
    [
      "Village[populationTotal]>(isPartOf|Lorestan_Province)>(isPartOf|Central_District_(Pol-e_Dokhtar_County))", 
      0.0949
    ], 
    [
      "Location[populationTotal]>(isPartOf|Razavi_Khorasan_Province)>(isPartOf|Bizaki_Rural_District)", 
      0.0952
    ]
  ], 
  "values": [
    30.0, 
    1.0, 
    337.0, 
    50.0, 
    20.0, 
    235.0, 
    410.0, 
    530.0, 
    14.0, 
    26.0, 
    139.0, 
    4.0, 
    156.0, 
    113.0, 
    2900.0, 
    308.0, 
    141.0, 
    270.0, 
    41.0, 
    24.0, 
    156.0, 
    52.0, 
    161.0, 
    3.0, 
    234.0, 
    142.0, 
    63.0, 
    8.0, 
    40.0, 
    80.0, 
    28.0, 
    106.0, 
    77.0, 
    42.0, 
    44.0, 
    49.0, 
    80.0, 
    3.0, 
    42.0, 
    931.0, 
    394.0, 
    931.0, 
    36.0, 
    53.0, 
    48.0, 
    17.0, 
    99.0, 
    34.0, 
    27.0, 
    8.0, 
    49.0, 
    209.0, 
    1920.0, 
    200.0, 
    60.0, 
    201.0, 
    43.0, 
    46.0, 
    522.0, 
    12.0, 
    57.0, 
    52.0, 
    579.0, 
    930.0, 
    22.0, 
    1035.0, 
    246.0, 
    104.0, 
    134.0, 
    16.0, 
    346.0, 
    102.0, 
    92.0, 
    162.0, 
    92.0, 
    8.0, 
    263.0, 
    14.0, 
    30.0, 
    316.0, 
    25.0, 
    400.0, 
    44.0, 
    299.0, 
    321.0, 
    44.0, 
    127.0, 
    262.0, 
    52.0, 
    56.0, 
    600.0, 
    3.0, 
    120.0, 
    8.0, 
    60.0, 
    194.0, 
    4.0, 
    19.0, 
    935.0, 
    36.0, 
    53.0, 
    80.0, 
    722.0, 
    2.0, 
    64.0, 
    12.0, 
    162.0, 
    65.0, 
    720.0, 
    44.0, 
    301.0, 
    44.0, 
    44.0, 
    36.0, 
    91.0, 
    69.0, 
    264.0, 
    40.0, 
    700.0, 
    69.0, 
    68.0, 
    52.0, 
    250.0, 
    70.0, 
    11.0, 
    5.0, 
    1.0, 
    94.0, 
    54.0, 
    180.0, 
    44.0, 
    78.0, 
    854.0, 
    428.0, 
    16.0, 
    69.0, 
    124.0, 
    182.0, 
    6.0, 
    240.0, 
    2.0, 
    90.0, 
    48.0, 
    48.0, 
    180.0, 
    44.0, 
    178.0, 
    39.0, 
    301.0, 
    120.0, 
    70.0, 
    45.0, 
    634.0, 
    153.0, 
    44.0, 
    52.0, 
    72.0, 
    4000.0, 
    266.0, 
    450.0, 
    114.0, 
    350.0, 
    83.0, 
    16.0, 
    121.0, 
    95.0, 
    22.0, 
    570.0
  ]
}
