{"invalid":["http://dbpedia.org/ontology/yearOfConstruction"],"labelling":{"property":{"avg":[["foundingYear",0.2233],["serviceStartYear",0.2311],["openingYear",0.2523],["activeYearsStartYear",0.2638],["deathYear",0.2714]],"maj":[["openingYear",4.0],["foundingYear",2.0],["activeYearsStartYear",2.0],["deathYear",1.0],["serviceStartYear",1.0]]},"type":{"avg":[["http://dbpedia.org/ontology/EducationalInstitution (foundingYear)",0.1639],["http://dbpedia.org/ontology/School (foundingYear)",0.1639],["http://dbpedia.org/ontology/Organisation (foundingYear)",0.2233],["http://dbpedia.org/ontology/Agent (foundingYear)",0.2233],["http://dbpedia.org/ontology/Agent (serviceStartYear)",0.2311],["http://dbpedia.org/ontology/OfficeHolder (serviceStartYear)",0.2311],["http://dbpedia.org/ontology/Person (serviceStartYear)",0.2311],["http://dbpedia.org/ontology/Station (openingYear)",0.2469],["http://dbpedia.org/ontology/Location (openingYear)",0.2469],["http://dbpedia.org/ontology/Infrastructure (openingYear)",0.2504],["http://dbpedia.org/ontology/ArchitecturalStructure (openingYear)",0.2504],["http://dbpedia.org/ontology/Place (openingYear)",0.2504],["http://dbpedia.org/ontology/RouteOfTransportation (openingYear)",0.254],["http://dbpedia.org/ontology/Bridge (openingYear)",0.254],["http://dbpedia.org/ontology/PublicTransitSystem (openingYear)",0.2615],["http://dbpedia.org/ontology/Organisation (openingYear)",0.2615],["http://dbpedia.org/ontology/Agent (openingYear)",0.2615],["http://dbpedia.org/ontology/Organisation (activeYearsStartYear)",0.2638],["http://dbpedia.org/ontology/Agent (activeYearsStartYear)",0.2638],["http://dbpedia.org/ontology/MilitaryUnit (activeYearsStartYear)",0.2657],["http://dbpedia.org/ontology/Saint (deathYear)",0.2714],["http://dbpedia.org/ontology/Person (deathYear)",0.2714],["http://dbpedia.org/ontology/Cleric (deathYear)",0.2714],["http://dbpedia.org/ontology/Agent (deathYear)",0.2714],["http://dbpedia.org/ontology/SportsTeam (foundingYear)",0.2827],["http://dbpedia.org/ontology/RugbyClub (foundingYear)",0.2827]],"maj":[["http://dbpedia.org/ontology/MilitaryUnit (activeYearsStartYear)",7.0],["http://dbpedia.org/ontology/Station (openingYear)",3.0],["http://dbpedia.org/ontology/School (foundingYear)",3.0],["http://dbpedia.org/ontology/Location (openingYear)",3.0],["http://dbpedia.org/ontology/Saint (deathYear)",2.0],["http://dbpedia.org/ontology/Infrastructure (openingYear)",2.0],["http://dbpedia.org/ontology/Organisation (foundingYear)",2.0],["http://dbpedia.org/ontology/Bridge (openingYear)",2.0],["http://dbpedia.org/ontology/OfficeHolder (serviceStartYear)",2.0],["http://dbpedia.org/ontology/Organisation (activeYearsStartYear)",2.0],["http://dbpedia.org/ontology/PublicTransitSystem (openingYear)",2.0],["http://dbpedia.org/ontology/ArchitecturalStructure (openingYear)",2.0],["http://dbpedia.org/ontology/Place (openingYear)",2.0],["http://dbpedia.org/ontology/Agent (activeYearsStartYear)",2.0],["http://dbpedia.org/ontology/RugbyClub (foundingYear)",2.0],["http://dbpedia.org/ontology/Agent (foundingYear)",2.0],["http://dbpedia.org/ontology/RouteOfTransportation (openingYear)",1.0],["http://dbpedia.org/ontology/EducationalInstitution (foundingYear)",1.0],["http://dbpedia.org/ontology/Agent (serviceStartYear)",1.0],["http://dbpedia.org/ontology/Person (deathYear)",1.0],["http://dbpedia.org/ontology/Cleric (deathYear)",1.0],["http://dbpedia.org/ontology/Agent (deathYear)",1.0],["http://dbpedia.org/ontology/Organisation (openingYear)",1.0],["http://dbpedia.org/ontology/Person (serviceStartYear)",1.0],["http://dbpedia.org/ontology/SportsTeam (foundingYear)",1.0],["http://dbpedia.org/ontology/Agent (openingYear)",1.0]]}},"neighbours":[["School[foundingYear]>(type|Single-sex_education)>(type|Boarding_school)",0.1639],["OfficeHolder[serviceStartYear]>(battle|World_War_I)",0.2311],["Station[openingYear]>(country|Japan)>(servingRailwayLine|%C5%8Cu_Main_Line)",0.2469],["Location[openingYear]>(operatedBy|East_Japan_Railway_Company)>(servingRailwayLine|%C5%8Cu_Main_Line)",0.2469],["MilitaryUnit[activeYearsStartYear]>(country|German_Empire)>(battle|Battle_of_the_Somme)",0.2507],["Bridge[openingYear]>(type|Swing_bridge)",0.254],["PublicTransitSystem[openingYear]>(location|England)",0.2615],["Saint[deathYear]>(beatifiedBy|Pope_John_Paul_II)",0.2714],["MilitaryUnit[activeYearsStartYear]>(country|German_Empire)>(battle|Battle_of_the_Somme)>(militaryBranch|German_Army_(German_Empire))",0.277],["RugbyClub[foundingYear]>(location|England)",0.2827]],"values":[1926.0,1907.0,1900.0,1883.0,1925.0,1936.0,1881.0,1908.0,1906.0,1890.0,1907.0,1910.0,1898.0,1910.0,1897.0,1868.0,1873.0,1926.0,1902.0,1914.0,1848.0,1920.0,1902.0,1938.0]}
