{
  "invalid": [
    "http://dbpedia.org/ontology/areaWater"
  ], 
  "labelling": {
    "property": {
      "avg": [
        [
          "areaWater", 
          0.0738
        ], 
        [
          "areaTotal", 
          0.0877
        ]
      ], 
      "maj": [
        [
          "areaTotal", 
          6.0
        ], 
        [
          "areaWater", 
          4.0
        ]
      ]
    }, 
    "type": {
      "avg": [
        [
          "http://dbpedia.org/ontology/PopulatedPlace (areaWater)", 
          0.0738
        ], 
        [
          "http://dbpedia.org/ontology/Region (areaWater)", 
          0.0738
        ], 
        [
          "http://dbpedia.org/ontology/Place (areaWater)", 
          0.0738
        ], 
        [
          "http://dbpedia.org/ontology/AdministrativeRegion (areaWater)", 
          0.0792
        ], 
        [
          "http://dbpedia.org/ontology/Town (areaTotal)", 
          0.0843
        ], 
        [
          "http://dbpedia.org/ontology/PopulatedPlace (areaTotal)", 
          0.0847
        ], 
        [
          "http://dbpedia.org/ontology/Place (areaTotal)", 
          0.0847
        ], 
        [
          "http://dbpedia.org/ontology/Settlement (areaTotal)", 
          0.0847
        ], 
        [
          "http://dbpedia.org/ontology/Location (areaTotal)", 
          0.0896
        ]
      ], 
      "maj": [
        [
          "http://dbpedia.org/ontology/Location (areaTotal)", 
          14.0
        ], 
        [
          "http://dbpedia.org/ontology/Town (areaTotal)", 
          5.0
        ], 
        [
          "http://dbpedia.org/ontology/AdministrativeRegion (areaWater)", 
          5.0
        ], 
        [
          "http://dbpedia.org/ontology/PopulatedPlace (areaWater)", 
          4.0
        ], 
        [
          "http://dbpedia.org/ontology/Region (areaWater)", 
          4.0
        ], 
        [
          "http://dbpedia.org/ontology/Place (areaWater)", 
          4.0
        ], 
        [
          "http://dbpedia.org/ontology/PopulatedPlace (areaTotal)", 
          2.0
        ], 
        [
          "http://dbpedia.org/ontology/Place (areaTotal)", 
          2.0
        ], 
        [
          "http://dbpedia.org/ontology/Settlement (areaTotal)", 
          2.0
        ]
      ]
    }
  }, 
  "neighbours": [
    [
      "Region[areaWater]", 
      0.0649
    ], 
    [
      "AdministrativeRegion[areaWater]", 
      0.0649
    ], 
    [
      "AdministrativeRegion[areaWater]>(state|North_Carolina)", 
      0.0802
    ], 
    [
      "Location[areaTotal]>(type|Census-designated_place)>(isPartOf|Nevada)", 
      0.0816
    ], 
    [
      "Town[areaTotal]>(country|India)>(22-rdf-syntax-ns#type|_Feature)", 
      0.0828
    ], 
    [
      "AdministrativeRegion[areaWater]>(state|Texas)", 
      0.0852
    ], 
    [
      "Town[areaTotal]>(country|India)", 
      0.0866
    ], 
    [
      "Location[areaTotal]>(timeZone|Indian_Standard_Time)>(isPartOf|Gujarat)", 
      0.0905
    ], 
    [
      "Location[areaTotal]>(type|Census-designated_place)>(isPartOf|Nevada)>(timeZone|Pacific_Time_Zone)", 
      0.0906
    ], 
    [
      "Location[areaTotal]>(timeZone|Indian_Standard_Time)>(isPartOf|Gujarat)>(country|India)", 
      0.0939
    ]
  ], 
  "values": [
    11037912.723087413, 
    151074679.53514794, 
    769469.207775282, 
    10295633.967649832, 
    2258770.432047428, 
    14048638.162732435, 
    12194351.305786436, 
    441235.2216388685, 
    20468374.810266312, 
    29223968.68709776, 
    1307477.2892840533, 
    19619866.044012353, 
    6300358.397373288, 
    37213124.891941406, 
    4191906.976827138, 
    227042078.84363174, 
    24596423.559208423, 
    43025698.91694808, 
    159601039.1017701, 
    457787959.89243084, 
    40649530.051759616, 
    1652793773.6982021, 
    20384481.824355975, 
    89907730.83955993, 
    14827201.59205869, 
    32449756.34470631, 
    46627597.159311004, 
    2105224.7710796082, 
    46432286.64666507, 
    12423203.576576598, 
    17508108.90065157, 
    4851224.912320272, 
    2665309.76289285, 
    10124741.634469884, 
    41075.24702102235, 
    58553084.19543097, 
    12434421.505125113, 
    1396009.9004709038, 
    41425445.65272331, 
    4625844428.822237, 
    7146642.535292375, 
    5692701.624594703, 
    5138004.920210829, 
    20023021.213076547, 
    168821412.865767, 
    59929899.78457248, 
    3960843.7275186265, 
    167605441.38948348, 
    372540308.44003993, 
    5807097.058308141, 
    347238757.1850462, 
    180974.53813098723, 
    2436494688.850881, 
    44688673.56421469, 
    132980.02668426672, 
    3398528.689286956, 
    32758065.23977482, 
    51156075.90018998, 
    45152644.192519225, 
    13147391.2634197, 
    19505888.375278633, 
    58050616.505455285, 
    66785478.19976684, 
    6461600.448967385, 
    2750165912.9788823, 
    10087121.1503911, 
    8279312.673522337, 
    54756879.50728988, 
    4347199.918788386, 
    4054574.891834626, 
    11013585.010872763, 
    378923409.1511799, 
    7135290.564813792, 
    1607649.5323532212, 
    5465092.808878726, 
    40348530.84609381, 
    11748967.933802705, 
    4762130.164808607, 
    2311189.6348215244, 
    8558062.31480163, 
    2380471482.4552007, 
    59256333.12551188, 
    1722433851.3133905, 
    6634152.203545421, 
    8364506.423704929, 
    19792823.188396513, 
    47081402.7471138, 
    2753977.451829175, 
    16578045.478105852, 
    103788578.51129334, 
    10883015.335846921, 
    16960003.78416388, 
    5791177.3324598605, 
    12627063.714861296, 
    11587768.574507538, 
    12895625.291930865, 
    19416573.139611572, 
    78655088.36769849, 
    21809376.98065816, 
    906477655.1549054, 
    1040655186.231128, 
    3415814.8292990066, 
    201546.15054795734, 
    186847274.31886363, 
    1775976.7697823914, 
    2167609.772471935, 
    4402993.31646258, 
    42816065.278067335, 
    106508103.4788087, 
    4382197.533993369, 
    729640.5236431877, 
    153661819.75093907, 
    17151448.217300937, 
    19444732.777036533, 
    1241975.2795157863, 
    165362027.8262826, 
    6716159.213015072, 
    457742642.7700233, 
    110913986.58683154, 
    1788303.1090250758, 
    9413754.750018703, 
    18114767.926853735, 
    13368929.180669941, 
    40749996.696590826, 
    119127452.1470864, 
    7498127.51808692, 
    3544962.5409624698, 
    3028056.6206395547, 
    9786908.185262186, 
    29341525.030383863, 
    10353227.85066776, 
    3890246057.0462317, 
    111362999.59595089, 
    5129551262.852793, 
    29079151.0227751, 
    104297553.44694617, 
    2819844.669523509, 
    595774611.6763825, 
    12896786.468245583, 
    39763313.70710562, 
    13011536.697288264, 
    1135481.4436062241, 
    20791167713.190372, 
    7077505.020128357, 
    58273306.27238761, 
    26684794.492472164, 
    6617594.843142316, 
    770060.6861562089, 
    2724244.7343864897, 
    573263853.5676122, 
    19827473.49513471, 
    29204834.46883399, 
    10105601.297231961, 
    8994166.248649418, 
    10350684.062694035, 
    3613399.1341022244, 
    61353024.34142464, 
    1224875624.5873585, 
    488604.4486137956, 
    811470850.970902, 
    940456680.7123597, 
    54927200.86485266, 
    1645779256.283291, 
    4685087.632957494, 
    288624695.8804071, 
    42146614.18820667, 
    2772331.0643081423, 
    1376117591.8249786, 
    5223871.095657714, 
    41009850.26272159, 
    1172380844.6591113, 
    79561761.17707564, 
    8495686.901858073, 
    2371645.486079154, 
    273392926.36642766, 
    14719559.648669925, 
    4426630.396646133, 
    116937062.85181844, 
    30679374.29070048, 
    24178240.219394818, 
    5663346.9713284485, 
    5901749.959876303, 
    2324553116.697554, 
    6578068.109698354, 
    6232004.2989657605, 
    78861658.77890994, 
    1536198343.8501606, 
    27145316.798067115, 
    17837295.97118886, 
    6255392.3081122115, 
    42680925.89067312, 
    94422582.49458382, 
    8210477.964807162, 
    46279255.68686011, 
    16701613.481384212, 
    38798183.426494256, 
    6600447.803435204, 
    73490168.55826811, 
    30461438.074511066, 
    39481123.061741345, 
    11234705.26320257, 
    12620988.295705602, 
    28497226.13644527, 
    34814963.07406368, 
    9752557.313130908, 
    9113865.567471739, 
    137054307.04685315, 
    10417879.088497639, 
    6212965.419008647, 
    38694921.18543986, 
    19625855.865906313, 
    27663924.025529098, 
    7715146.536057019, 
    443305022.6120446, 
    11471557.114761734, 
    4885854.184809047, 
    19133955.58385699, 
    33230605.191540595, 
    8079261.969436857, 
    64979986.774591684, 
    4890409.544032018, 
    5975850.580738861, 
    9028304.664675023, 
    237629140.99507743, 
    9162652.534069045, 
    12364257.151404046, 
    62873313.687038876, 
    76435790.79471695, 
    6921446.636384131, 
    5680215.201835764, 
    4195246.8253157465, 
    26434769.9016766, 
    41254413.85140279, 
    15899197.920677012, 
    18134976.243083067, 
    6609650.40624251, 
    32076600.48080815, 
    459703.42575778486, 
    1345233756.7745323, 
    4893816.589800927, 
    833780483.0079408, 
    44013302.05641264, 
    5679522.446092568, 
    34846269.46590722, 
    17218923.514662102, 
    27981792.47261947, 
    4682563.9395599365, 
    6530284.668936327, 
    539659.5657155957, 
    19699018.911653023, 
    19848248.722522344, 
    719719.0511674209, 
    101714455.34040724, 
    1368304407.0357008, 
    1407722.4200449465, 
    6977067.915326546, 
    616376619.8981496, 
    3225404.6456016316, 
    19286277.90643599, 
    17071183.096177317, 
    18609188.012323406, 
    19015397.49642552, 
    14893997.422038075, 
    9359685.860831952, 
    2503871.0316200913, 
    16445934.337036807, 
    7182226.387755642, 
    70616299.36991721, 
    37001881.6220533, 
    21667661.057432227, 
    12099928.391241416, 
    16986941.13381929, 
    41400573.99140652, 
    3772168.410481219, 
    606477.0649423765, 
    6081249.347029615, 
    175448323.728923, 
    96657071.52377932, 
    806474485.7745169, 
    10862180.328444816, 
    3687324977.06276, 
    43319814.06270904, 
    13167185.32529015, 
    3068264.6946202484, 
    14146382.13332834, 
    13817149.19811463, 
    9797786.160710573, 
    18561894.858041856, 
    14191210.860462306, 
    14083420.558873694, 
    7545111.059409875, 
    597716962.0307629, 
    21522258.262636513, 
    8065878.786313169, 
    1642339.7539904853, 
    4955457.964193866, 
    10031776.369916622, 
    339110042.66051954, 
    3051351.0816701422, 
    7166097.320086625, 
    7300338.778617147, 
    46514829.897313155, 
    45639993.082221076, 
    31873754.832740456, 
    32635920.47628236, 
    5054723.524276237, 
    5632475.303287432, 
    478453.3359209193, 
    9068831.137582414, 
    2255810.0108142644, 
    27867531.77881872, 
    20558014.9281147, 
    21866646.43338951, 
    54056892.49623151, 
    12028288.58058737, 
    20820543.962519903, 
    13145161.86742052, 
    14268652.692952909, 
    477602.44475978496, 
    68303146.68772778, 
    4563493.737060647, 
    6867311.482613416, 
    10857639.640892453, 
    4059920.948519857, 
    355724482.0462662, 
    26255336.81452507, 
    128187796.18489087, 
    60960236.25913938, 
    41269558.426054806, 
    4083716.9732896797, 
    23912992.840075873
  ]
}
