{
  "invalid": [
    "http://dbpedia.org/ontology/elevation"
  ], 
  "labelling": {
    "property": {
      "avg": [
        [
          "elevation", 
          0.0686
        ], 
        [
          "populationTotal", 
          0.0834
        ], 
        [
          "populationDensity", 
          0.0879
        ]
      ], 
      "maj": [
        [
          "elevation", 
          5.0
        ], 
        [
          "populationDensity", 
          3.0
        ], 
        [
          "populationTotal", 
          2.0
        ]
      ]
    }, 
    "type": {
      "avg": [
        [
          "http://dbpedia.org/ontology/Town (elevation)", 
          0.0639
        ], 
        [
          "http://dbpedia.org/ontology/City (elevation)", 
          0.0675
        ], 
        [
          "http://dbpedia.org/ontology/PopulatedPlace (elevation)", 
          0.0686
        ], 
        [
          "http://dbpedia.org/ontology/Place (elevation)", 
          0.0686
        ], 
        [
          "http://dbpedia.org/ontology/Settlement (elevation)", 
          0.069
        ], 
        [
          "http://dbpedia.org/ontology/Village (elevation)", 
          0.0775
        ], 
        [
          "http://dbpedia.org/ontology/Place (populationTotal)", 
          0.0834
        ], 
        [
          "http://dbpedia.org/ontology/Settlement (populationTotal)", 
          0.0834
        ], 
        [
          "http://dbpedia.org/ontology/PopulatedPlace (populationTotal)", 
          0.0834
        ], 
        [
          "http://dbpedia.org/ontology/Village (populationTotal)", 
          0.0842
        ], 
        [
          "http://dbpedia.org/ontology/Settlement (populationDensity)", 
          0.0849
        ], 
        [
          "http://dbpedia.org/ontology/Village (populationDensity)", 
          0.0849
        ], 
        [
          "http://dbpedia.org/ontology/Place (populationDensity)", 
          0.0849
        ], 
        [
          "http://dbpedia.org/ontology/PopulatedPlace (populationDensity)", 
          0.0849
        ], 
        [
          "http://dbpedia.org/ontology/Location (populationDensity)", 
          0.0896
        ]
      ], 
      "maj": [
        [
          "http://dbpedia.org/ontology/Village (populationTotal)", 
          7.0
        ], 
        [
          "http://dbpedia.org/ontology/PopulatedPlace (elevation)", 
          5.0
        ], 
        [
          "http://dbpedia.org/ontology/Place (elevation)", 
          5.0
        ], 
        [
          "http://dbpedia.org/ontology/Location (populationDensity)", 
          5.0
        ], 
        [
          "http://dbpedia.org/ontology/Settlement (elevation)", 
          4.0
        ], 
        [
          "http://dbpedia.org/ontology/Place (populationTotal)", 
          2.0
        ], 
        [
          "http://dbpedia.org/ontology/Settlement (populationTotal)", 
          2.0
        ], 
        [
          "http://dbpedia.org/ontology/PopulatedPlace (populationTotal)", 
          2.0
        ], 
        [
          "http://dbpedia.org/ontology/Village (populationDensity)", 
          2.0
        ], 
        [
          "http://dbpedia.org/ontology/Village (elevation)", 
          1.0
        ], 
        [
          "http://dbpedia.org/ontology/City (elevation)", 
          1.0
        ], 
        [
          "http://dbpedia.org/ontology/Settlement (populationDensity)", 
          1.0
        ], 
        [
          "http://dbpedia.org/ontology/Town (elevation)", 
          1.0
        ], 
        [
          "http://dbpedia.org/ontology/Place (populationDensity)", 
          1.0
        ], 
        [
          "http://dbpedia.org/ontology/PopulatedPlace (populationDensity)", 
          1.0
        ]
      ]
    }
  }, 
  "neighbours": [
    [
      "Town[elevation]", 
      0.0639
    ], 
    [
      "PopulatedPlace[elevation]", 
      0.0669
    ], 
    [
      "Settlement[elevation]", 
      0.067
    ], 
    [
      "City[elevation]", 
      0.0675
    ], 
    [
      "Village[elevation]", 
      0.0775
    ], 
    [
      "Village[populationTotal]>(isPartOf|West_Azerbaijan_Province)>(isPartOf|Central_District_(Urmia_County))", 
      0.0777
    ], 
    [
      "Village[populationDensity]>(isPartOf|Wisconsin)", 
      0.0849
    ], 
    [
      "Location[populationDensity]>(isPartOf|Missouri)", 
      0.0886
    ], 
    [
      "Village[populationTotal]>(isPartOf|West_Azerbaijan_Province)>(isPartOf|Central_District_(Urmia_County))>(22-rdf-syntax-ns#type|_Feature)", 
      0.0891
    ], 
    [
      "Location[populationDensity]>(isPartOf|Wisconsin)>(type|Village_(United_States))", 
      0.0902
    ]
  ], 
  "values": [
    347.2820811846943, 
    575.81064007325, 
    133.27347824163886, 
    457.56160821456353, 
    359.41395966111025, 
    277.7404260056448, 
    222.66868846369252, 
    1089.4359023133545, 
    204.04809545053556, 
    8.907665471523309, 
    451.3260517124078, 
    318.41554064506573, 
    57.323945247188696, 
    52.70801448480895, 
    9.617026768077857, 
    249.61360257818666, 
    317.19271646603994, 
    194.28811363691548, 
    176.59022955367502, 
    357.37830937423155, 
    158.17701917127206, 
    280.42038197139783, 
    133.35142353446437, 
    369.75548089563915, 
    344.93786874019156, 
    7.429801885830429, 
    391.5147147016326, 
    19.657657630123037, 
    87.11051377436483, 
    0.0, 
    360.5542523003506, 
    180.60529180792344, 
    79.11156542808115, 
    207.17425773150813, 
    44.45562204712529, 
    214.17667640511084, 
    320.7821445511464, 
    620.0661066281394, 
    163.95042199925552, 
    293.78979929365846, 
    309.21596515120655, 
    209.3221606883616, 
    327.01717051227735, 
    311.9654392393873, 
    9.804947934450947, 
    91.51456966267615, 
    2.879462458132062, 
    239.11989044908574, 
    1122.6139395389116, 
    1609.840298196165, 
    198.14865688423873, 
    301.9560466311368, 
    29.93043572958758, 
    372.57817417938116, 
    98.57076400928239, 
    409.0823129571974, 
    322.06489731454343, 
    70.28897899719891, 
    331.3610076642365, 
    361.3622847163287, 
    262.3236043431681, 
    420.9165936322948, 
    2503.9287566521457, 
    757.4689355774503, 
    381.2865691424778, 
    1914.8109768181616, 
    93.0333624286926, 
    298.9408057984456, 
    269.17230717676955, 
    62.97115604095872, 
    286.40628084729707, 
    264.4305307873767, 
    34.35176353273859, 
    1628.2436543225897, 
    54.92694826158818, 
    83.64364178146079, 
    175.2215802773708, 
    152.52034361342592, 
    3282.8818246554147, 
    300.4841116123645, 
    218.60553359930222, 
    0.9564682479015805, 
    470.7289564605362, 
    367.8072516904629, 
    1184.8502755925404, 
    793.6148960134935, 
    233.05387973300822, 
    333.35864606864715, 
    278.73287197095203, 
    185.60191542563646, 
    957.5032070520538, 
    467.32998045209575, 
    310.3878560594464, 
    252.71023380808364, 
    437.03763446368976, 
    175.6843721098192, 
    2162.555090837389, 
    132.63225821903092, 
    540.0123824094004, 
    283.65007697391223
  ]
}
