{
  "invalid": [
    "http://dbpedia.org/ontology/elevation"
  ], 
  "labelling": {
    "property": {
      "avg": [
        [
          "elevation", 
          0.0538
        ], 
        [
          "populationDensity", 
          0.0771
        ]
      ], 
      "maj": [
        [
          "elevation", 
          6.0
        ], 
        [
          "populationDensity", 
          4.0
        ]
      ]
    }, 
    "type": {
      "avg": [
        [
          "http://dbpedia.org/ontology/City (elevation)", 
          0.0161
        ], 
        [
          "http://dbpedia.org/ontology/Village (elevation)", 
          0.0485
        ], 
        [
          "http://dbpedia.org/ontology/PopulatedPlace (elevation)", 
          0.0538
        ], 
        [
          "http://dbpedia.org/ontology/Place (elevation)", 
          0.0538
        ], 
        [
          "http://dbpedia.org/ontology/Settlement (elevation)", 
          0.0645
        ], 
        [
          "http://dbpedia.org/ontology/Location (populationDensity)", 
          0.0754
        ], 
        [
          "http://dbpedia.org/ontology/Town (elevation)", 
          0.0755
        ], 
        [
          "http://dbpedia.org/ontology/Village (populationDensity)", 
          0.0763
        ], 
        [
          "http://dbpedia.org/ontology/Settlement (populationDensity)", 
          0.0777
        ], 
        [
          "http://dbpedia.org/ontology/Place (populationDensity)", 
          0.0777
        ], 
        [
          "http://dbpedia.org/ontology/PopulatedPlace (populationDensity)", 
          0.0777
        ], 
        [
          "http://dbpedia.org/ontology/Town (populationDensity)", 
          0.0802
        ]
      ], 
      "maj": [
        [
          "http://dbpedia.org/ontology/Settlement (elevation)", 
          8.0
        ], 
        [
          "http://dbpedia.org/ontology/PopulatedPlace (elevation)", 
          6.0
        ], 
        [
          "http://dbpedia.org/ontology/Place (elevation)", 
          6.0
        ], 
        [
          "http://dbpedia.org/ontology/Village (populationDensity)", 
          5.0
        ], 
        [
          "http://dbpedia.org/ontology/Settlement (populationDensity)", 
          3.0
        ], 
        [
          "http://dbpedia.org/ontology/Place (populationDensity)", 
          3.0
        ], 
        [
          "http://dbpedia.org/ontology/Location (populationDensity)", 
          3.0
        ], 
        [
          "http://dbpedia.org/ontology/PopulatedPlace (populationDensity)", 
          3.0
        ], 
        [
          "http://dbpedia.org/ontology/Town (populationDensity)", 
          2.0
        ], 
        [
          "http://dbpedia.org/ontology/Village (elevation)", 
          1.0
        ], 
        [
          "http://dbpedia.org/ontology/City (elevation)", 
          1.0
        ], 
        [
          "http://dbpedia.org/ontology/Town (elevation)", 
          1.0
        ]
      ]
    }
  }, 
  "neighbours": [
    [
      "City[elevation]", 
      0.0161
    ], 
    [
      "Village[elevation]", 
      0.0485
    ], 
    [
      "Settlement[elevation]", 
      0.0505
    ], 
    [
      "PopulatedPlace[elevation]", 
      0.051
    ], 
    [
      "Location[populationDensity]>(isPartOf|Wisconsin)>(type|Village_(United_States))", 
      0.0754
    ], 
    [
      "Village[populationDensity]>(isPartOf|Wisconsin)>(type|Village_(United_States))", 
      0.0754
    ], 
    [
      "Town[elevation]", 
      0.0755
    ], 
    [
      "Village[populationDensity]>(isPartOf|Wisconsin)", 
      0.0775
    ], 
    [
      "Town[populationDensity]>(timeZone|Mountain_Time_Zone)", 
      0.0802
    ], 
    [
      "Settlement[elevation]>(country|France)>(region|Provence-Alpes-C%C3%B4te_d'Azur)>(department|Vaucluse)", 
      0.0813
    ]
  ], 
  "values": [
    913.2263993265295, 
    126.82730471296685, 
    28.295442668667988, 
    350.19438390938075, 
    155.2414502352668, 
    262.90198020360907, 
    76.2368031982059, 
    257.4772207786582, 
    304.1149930591595, 
    45.19916139467748, 
    36.84034915211246, 
    205.51437714455824, 
    349.5791760372616, 
    91.60330902267438, 
    83.35725391747734, 
    318.47883625231304, 
    87.82938422892072, 
    470.1929969213306, 
    408.05110667743537, 
    206.83350101335765, 
    7.94036062135275, 
    27.779630787440645, 
    1160.6604223329377, 
    648.4163786830801, 
    530.1471778675469, 
    347.5952900743264, 
    17.49468490327469, 
    36.10181333155772, 
    429.5752783563209, 
    344.1855783508282, 
    205.37490187568534, 
    349.9973287991241, 
    401.0718865023641, 
    241.58028576862674, 
    509.72599505456606, 
    259.0384186219371, 
    166.57339221104863, 
    5.969046278757027, 
    380.5245073913041, 
    321.4245054073863, 
    10.619002755232254, 
    103.27794391629706, 
    279.99280341810254, 
    102.66426886969927, 
    276.957982889413, 
    271.8607866590119, 
    1.9191033702966596, 
    60.77625960599766, 
    330.62611455953345, 
    65.96435603106478, 
    333.8074475428668, 
    57.04062970372327, 
    222.07231425610095, 
    367.4723137930375, 
    327.3202166660183, 
    201.00236798563284, 
    490.46347812021486, 
    11.528316553321964, 
    1063.210285640025, 
    232.40846471116336, 
    35.0065368336764, 
    196.64899702906737, 
    30.78905081352765, 
    79.35286077311994, 
    252.22426844315748, 
    335.9955975603878, 
    292.99915354962, 
    237.71170285867328, 
    316.8205005045311, 
    298.04291054256834, 
    377.41718248061477, 
    1392.5205497123445, 
    952.1471333981923, 
    231.71651475058215, 
    176.89752451400958, 
    539.7586696834342, 
    330.9129330410973, 
    116.76418498405043, 
    251.17095042730506, 
    254.1855578393103, 
    316.66823340891574, 
    497.0802469037815, 
    164.78755251626885, 
    180.86186244157392, 
    132.86790553270893, 
    439.4699891275459, 
    399.01649969078306, 
    226.11510374233376, 
    87.8537501362672, 
    263.72521268258765, 
    28.365385732209994, 
    214.03592749468132, 
    260.85613836571906, 
    389.43510827935813, 
    287.21337457953854, 
    317.3115767567653, 
    108.20178852762787, 
    166.72056931474225, 
    123.95089768250958, 
    299.6769165975246, 
    95.9935861803728, 
    283.3780224216938, 
    0.9657829146190083, 
    183.6900308724222, 
    424.2578575751115, 
    221.44738731068577, 
    71.85090572968986, 
    185.30355545119542, 
    4.031335310518127, 
    1339.9230767937388, 
    380.80664947711347, 
    4.969655929683076, 
    319.5549937547572, 
    333.2658137479161, 
    83.39262486938011, 
    438.55637785428087, 
    150.4039889378726, 
    1.9169055007238676, 
    253.0535937468167, 
    31.858981683195246, 
    9.960189667968248, 
    23.860822073030285, 
    272.3370643871269, 
    116.98681320945246, 
    150.21538281354566, 
    182.7269199154976, 
    327.44879119619475, 
    1325.0921951729495, 
    21.61591740316966, 
    27.708987904874466, 
    414.17672008825514, 
    219.790679104663, 
    193.28433410909463, 
    60.821058260773526, 
    187.48959828291362, 
    74.54649819534855, 
    481.0381178241327, 
    317.9079746541373, 
    16.13456273182577, 
    157.38951845465496, 
    134.18027968858715, 
    199.59606294024096, 
    72.75397676720372, 
    238.27626005077872, 
    208.11615138235288, 
    380.57449045728146, 
    243.0142733819404, 
    1306.1975258306759, 
    337.1033939345101, 
    244.12551688002756, 
    347.9600454420569, 
    2408.211431769417, 
    1364.4309773787768, 
    311.4426042693886, 
    319.36862460048116, 
    235.5318664233455, 
    865.3337886793561, 
    439.7082784609937, 
    445.88899088697497, 
    513.532154501111, 
    318.46774617713055, 
    271.4719433224133, 
    108.44714319645018, 
    412.594449209739, 
    33.52587687247721, 
    11.511017346024328, 
    614.1637330999602, 
    384.6360822538776, 
    453.1963837204122, 
    11.177651289232331, 
    282.71779667570905, 
    267.30645772295634, 
    197.96525771752707, 
    215.58545448853926, 
    246.301773165804, 
    44.05748311730709, 
    205.86457276387372, 
    262.5223467742201, 
    1367.5267433254726, 
    3.9159291944633745, 
    116.81904111429, 
    319.75781209033363, 
    855.127826935647, 
    178.37387286201323, 
    268.94719952673563, 
    303.5198650803877, 
    33.66246655929214, 
    96.27529101859596, 
    359.6299258834358, 
    285.94185812905, 
    410.5568782055196, 
    244.76747427093656, 
    231.65752631476974, 
    116.516418614948, 
    73.88756481206114, 
    95.59280508077315, 
    437.3507226430748, 
    199.4452758178736, 
    234.5526998859347, 
    420.67844445338255, 
    900.801302250864, 
    220.89454509315394, 
    174.40403667335647, 
    271.4984418405478, 
    13.243742530830437, 
    258.04202255326345, 
    196.73427190509145, 
    221.68690057274628, 
    324.43535920620434, 
    282.08832881727915, 
    178.47085303034203, 
    405.48177992737794, 
    5.111958574414068, 
    206.68440919598706, 
    42.1267673079196, 
    41.60446081409283, 
    2.2181518942888085, 
    426.8916928255744, 
    341.67670794910805, 
    525.4485128165288, 
    144.30799779772286, 
    335.3090586036531, 
    238.32484990049213, 
    38.355160639961625, 
    9.422546472754005, 
    128.67370349011912, 
    561.1251952683195, 
    96.38533959356354, 
    252.8727465929964, 
    2.09170954131085, 
    342.84604836474307, 
    636.0179434827214, 
    2.609759989697253, 
    439.4074951972526, 
    372.99373213866045, 
    30.02436663342572, 
    235.36642062065528, 
    143.83439956803812, 
    15.162027685216149, 
    5.961072509609823, 
    305.15254853065096, 
    27.973050416235075, 
    456.2675771483615, 
    42.98660923625561, 
    2.1826413243650524, 
    131.81677310296652, 
    103.06411155480279, 
    138.2034219530359, 
    404.6629891953531, 
    212.4538670793131, 
    309.1339001743802, 
    402.1653849382313, 
    379.06619855355524, 
    143.40093011823035, 
    290.18950102618675, 
    51.68301314026552, 
    270.1245887291986, 
    248.3811050540596, 
    4.0740314925683165, 
    197.25684510600615, 
    77.0689255762306, 
    251.80332837220712, 
    1700.796874838863, 
    130.69416128735102, 
    239.21952455342526, 
    426.39041211538284, 
    764.088918762915, 
    83.05749994788707, 
    326.0653497170181, 
    297.51538378598366, 
    420.9025124842921, 
    218.94380129263917, 
    7.051964097597484, 
    306.7886028248768, 
    658.3141391609544, 
    186.39194763996986, 
    399.2352474624122, 
    106.88428036519649, 
    260.8534372632459, 
    332.6813976390402, 
    1137.3724032449322, 
    218.54357108383337, 
    73.99433552995083, 
    119.46625709945853, 
    17.404321777535625, 
    68.02215155899098, 
    1004.02821285463, 
    433.4006627355597, 
    315.2594684810954, 
    47.676783230155266, 
    391.4216285295785, 
    420.31665784504185, 
    399.7417746706396, 
    382.8466427703628, 
    1853.469869976153, 
    466.42991046085126, 
    234.50485878096956, 
    347.91010944659627, 
    186.2995118291054, 
    136.33852495778052, 
    124.39918541177822, 
    225.00136126948638, 
    241.2033078873443, 
    163.66671191091768, 
    557.0209612931724, 
    1.9435326053892767, 
    430.6311568124966, 
    666.5851582414688, 
    304.7860199555187, 
    442.65522135201996, 
    198.15366558290782, 
    2933.7468730021515, 
    396.3868293987528, 
    147.91220575314955, 
    655.794481950959, 
    503.80046637854554, 
    442.0566615731191, 
    110.32202233371045, 
    525.4142058032401, 
    698.3923319952693, 
    32.97716552594133, 
    283.82098835399233, 
    321.1914955452379, 
    540.3295632304021, 
    147.4242548473915, 
    268.3557536245051, 
    -13.184348143881309, 
    65.77064575571079, 
    207.79383704799005, 
    430.7482565888152, 
    6.3511983685407225, 
    436.73990256276267, 
    271.28023798553596, 
    340.21742867576125, 
    364.39207043636685, 
    185.86572952041593, 
    189.54066175798152, 
    654.142076349518, 
    241.23688889816984, 
    290.6844637033117, 
    172.45318840776872, 
    44.32757786925289, 
    349.62938598327094, 
    113.89939153215252, 
    1080.495144435794, 
    79.44659776376169, 
    50.93987401694857, 
    113.75118246581965, 
    269.5566317292483, 
    43.362339459187254, 
    227.89690214177838, 
    345.08032267339564, 
    416.80082088196207, 
    383.0835960377975, 
    484.1478658390648, 
    307.40547529602975, 
    14.03637296187579, 
    637.5538393142202, 
    320.72818517550536, 
    184.70839426648539, 
    208.16464394891847, 
    340.8121421071581, 
    300.9413882389267, 
    138.1085649702574, 
    516.5065834548084, 
    92.46313897974376, 
    367.28387316863314, 
    335.88669563851795, 
    336.26530191928185, 
    307.2839254306931, 
    1474.7676175301217, 
    360.92067481388625, 
    475.6354236576399, 
    424.461694373817, 
    41.16597368928364, 
    60.76216336325413, 
    366.79926459648703, 
    334.27813656812197, 
    146.80276536805374, 
    73.88316857390252, 
    282.6674537155275, 
    380.79316430393885, 
    334.00259364856095, 
    403.2151861714666, 
    269.1939360545419, 
    287.59614057482923, 
    270.15040838026414, 
    265.5503948201327, 
    262.81738498168113, 
    209.0467629398958, 
    404.3905868992745, 
    103.9877439935752, 
    316.42585098876776, 
    1253.020132719888, 
    475.146619262623, 
    1333.0622012174867, 
    337.97579632198153, 
    33.60544634679892, 
    24.550920929068685, 
    50.95620328003304, 
    225.88579754996917, 
    2.8555768505932004, 
    3.0274112965818802, 
    213.7552602231846, 
    6.098766478865518, 
    238.14486328055287, 
    365.48397991332166, 
    155.5215220681962, 
    309.3761084565439, 
    430.3636796920908, 
    252.29120597328523, 
    17.48486104284238, 
    227.99164017199234, 
    515.6660855724497, 
    367.6252663981086, 
    383.6628599765259, 
    274.7045829329257, 
    1285.981161404229, 
    36.160338174311924, 
    638.1790270698444, 
    58.54882334425276, 
    1267.6433395202378, 
    306.6358112182415, 
    262.6959970848487, 
    657.1454789036064, 
    17.504162638942198, 
    1132.979815842405, 
    282.6920029866205, 
    382.1967009445895, 
    120.39204005423075, 
    276.4349746471886, 
    218.9819221396239, 
    492.70023940501727, 
    130.6185910856204, 
    17.095896244944065, 
    955.739022762008, 
    263.8263372932091, 
    360.93343459868015, 
    280.1136332134857, 
    15.398793363102284, 
    62.72015513062951, 
    210.10618530899518, 
    273.83599561570725, 
    10.287855324447632, 
    329.5651664410336, 
    569.9335026458831, 
    907.4969134382582, 
    307.1334977155106, 
    408.8464742616135, 
    59.35344097105607, 
    265.98423928054893, 
    492.0064931429867, 
    265.468053141897, 
    70.87881232657529, 
    205.33817680869308, 
    383.12525339588865, 
    101.30409579443574, 
    65.29084303451745, 
    433.93452499884404, 
    279.9739546674472, 
    1102.3576795012245, 
    453.96132375379835, 
    444.39693187290703, 
    252.11508747368396, 
    828.937083735622, 
    535.3932723200254, 
    715.6225959983864, 
    844.0681902147862, 
    335.65059949932754, 
    383.03736765494835, 
    5.713086148145874, 
    63.21600473001647, 
    569.3149822596095, 
    396.339585870375, 
    62.347685061144574, 
    101.1815877680755, 
    326.6760706965887, 
    284.1534674614753, 
    128.83887137662936, 
    170.63282104167513, 
    358.51389020806516, 
    324.60901737882625, 
    62.07167764507406, 
    84.47793563580437, 
    459.5043917138241, 
    1431.596851666186, 
    347.2265452168041, 
    234.00482904114193, 
    321.14346071651505, 
    292.36281523332053, 
    321.4925751874431, 
    98.24524648062179, 
    205.1077205868417, 
    298.87205666409005, 
    294.3292857995577, 
    220.9160673715311, 
    1356.4755065090978, 
    245.92826221049484, 
    436.1920949420071, 
    252.21504196753384, 
    14.348257170888377, 
    294.93801975150626, 
    1400.3214792953916, 
    146.8473699106726, 
    258.56295997962275, 
    176.4454521758931, 
    82.81641494387277, 
    239.84516820300914, 
    2.9374101728643374, 
    263.1227805748968, 
    2557.0444613997897, 
    328.21715679412193, 
    238.59176426884534, 
    425.53861648671636, 
    72.65622065952203, 
    1.9843043425305955, 
    336.8887192596148, 
    784.3388489606925, 
    23.913471703096693, 
    119.12200505267484, 
    333.8157966623914, 
    4.798855149832532, 
    467.046028547866, 
    192.88601987349028, 
    703.1390183500906, 
    439.15518526354174, 
    340.91205056285673, 
    135.94713074369244, 
    281.73291118429125, 
    12.184244906688527, 
    269.6886812081795, 
    309.6208468458673, 
    117.15890785306685, 
    91.19629597136567, 
    107.16653030416956, 
    337.68395549607254, 
    654.9174334306605, 
    1033.6483136766717, 
    999.5437148192087, 
    105.44066035668648, 
    74.23044493859824, 
    650.417500138685, 
    1178.6768348253559, 
    256.27027254293034, 
    70.89377363643686, 
    135.4278361962834, 
    204.80847463209136, 
    287.9298362311619, 
    312.93298183787897, 
    94.232368483045, 
    231.80811130383594, 
    201.90824770481908, 
    703.3508220030266, 
    184.97188019931758, 
    338.69304798186033, 
    533.351136082719, 
    1727.9688454761156, 
    357.494190181005, 
    323.42307170089424, 
    231.39567322631765, 
    149.3029208874532, 
    274.43615834731366, 
    333.71088379345525, 
    984.4135698660593, 
    244.86652058933478, 
    267.1871836750289, 
    279.9948782077964, 
    273.4253619546909, 
    247.895922595613, 
    164.5197976612991, 
    193.38344826423378, 
    96.73957981947545, 
    54.76358571039619, 
    381.1688080033019, 
    173.12073941654938, 
    537.6851739254749, 
    327.225821627251, 
    648.1839817879489, 
    306.49740051973663, 
    19.098165279792266, 
    315.4438230153413, 
    448.663939603542, 
    47.087255254376636, 
    56.0678789563297, 
    304.3395200143147, 
    94.97389711471932, 
    201.94413376476194, 
    390.49646964936045, 
    274.02651592501434, 
    143.55196231313326, 
    111.14255116150886, 
    42.700386919599254, 
    410.823340497978, 
    396.7600003333315, 
    155.02661587378657, 
    407.4081352219759, 
    280.51255086782976, 
    71.02731180726539, 
    181.17034116104801, 
    224.364526420123, 
    436.9853464745149, 
    92.26470568388883, 
    266.43748914965596, 
    225.59006172155966, 
    101.73688876428128, 
    555.235526622566, 
    138.8414999545324, 
    441.57711456367844, 
    179.39140701604722, 
    679.0679056781424, 
    379.45991936451117, 
    374.44097476585733, 
    272.06538833079054, 
    114.51766788994661, 
    2.8526682252949156, 
    245.6172520720709, 
    55.163506465943776, 
    480.83334952314885, 
    350.8697364692931, 
    39.039102681330355, 
    151.15236852704464, 
    1233.2179373619724, 
    89.40116163235999, 
    655.0980067610997, 
    650.5200504145529, 
    177.44045976770838, 
    355.75564706539, 
    451.9067140753432, 
    307.52132198865536, 
    358.1719043266166, 
    238.40689132226723, 
    256.3520188930264, 
    145.22174229366416, 
    260.6348090566264, 
    12.009402902812164, 
    24.127963058711806, 
    119.13435714752237, 
    266.84550953840284, 
    172.43494931420702, 
    370.19283099436245, 
    716.4019914175304, 
    262.8651057297739, 
    35.09132758549287, 
    586.2682318732883, 
    95.48012278696984, 
    293.326064954883, 
    364.75956466540157, 
    122.35130713861953, 
    1590.8255645977347, 
    342.14816755790935, 
    58.38501183578215, 
    -18.033679341771588, 
    35.189498126989314, 
    92.84193944500566, 
    456.4428190770949, 
    289.56111507040515, 
    274.1552250170762, 
    273.3580021904545, 
    300.43835299446545, 
    738.4650848781588, 
    512.6660958704031, 
    224.4945054622525, 
    669.8081985508811, 
    295.1805190612814, 
    176.8747367113608, 
    44.606402757645476, 
    381.1262472858144, 
    287.2131046047638, 
    281.9269945494948, 
    265.0885034832346, 
    15.271580956656546, 
    383.4836916264821, 
    188.85207907408923, 
    286.0107659479804, 
    1566.3665952121373, 
    429.01690931736505, 
    252.62343994109278, 
    1668.0999188933374, 
    37.549849376291355, 
    11.21727967222183, 
    149.7221225649561, 
    414.78186976444226, 
    283.0618604386511, 
    94.4812935706238, 
    266.0714261705597, 
    379.4779716710123, 
    364.46081381573197, 
    -3.1011312160610114, 
    201.8341592148981, 
    771.404513204083, 
    76.51361383567391, 
    100.89149446958527, 
    -3.1073788740305375, 
    -32.465362801368016, 
    2675.3457081634942, 
    2329.455867017332, 
    241.30270109197093, 
    131.80522800686265, 
    291.843738011667, 
    282.5615320539748, 
    264.42484200889675, 
    470.3568327021831, 
    374.3321491098581, 
    34.434400135599965, 
    221.13978539491237, 
    168.41335558974993, 
    221.81762503474684, 
    263.1169452862493, 
    299.5039142907014, 
    169.93494323257102, 
    1701.837551467813, 
    257.025084945226, 
    388.49588066479095, 
    365.95036081852635, 
    48.18424868185757, 
    420.7315885684155, 
    3.9661663328625507, 
    553.0812485544748, 
    28.893719120996018, 
    184.04136625178614, 
    117.74283230425283, 
    838.5727383177306, 
    196.1485337344583, 
    220.48429361050506, 
    277.6210340996594, 
    41.47510803462855, 
    339.0739801805232, 
    28.51450074403756, 
    377.16385850007015, 
    320.11837313445477, 
    376.2469530617276, 
    4084.0201512494023, 
    136.04917413883842, 
    284.3920058202468, 
    262.6325510467698, 
    69.43303128488698, 
    1802.841635985117, 
    560.569285119747, 
    1863.1260097507186, 
    291.2588018438226, 
    375.2782606309903, 
    200.88905376119433, 
    90.87998723962343, 
    283.01952968823093, 
    271.63984632746843, 
    6.313868624549096, 
    211.00001198184108, 
    709.5903563107998, 
    1402.544380337826, 
    40.11527459404115, 
    169.15550744795658, 
    69.44709262447259, 
    597.2499531613119, 
    364.1789457172167, 
    369.64002768822496, 
    325.60325845728187, 
    367.0013135110969, 
    294.8269688081139, 
    509.97398241762954, 
    348.5456268561736, 
    425.088389107438, 
    373.5491997528577, 
    342.70716986213137, 
    200.1740860378212, 
    813.5345082201917, 
    587.6390375482551, 
    154.29395612739017, 
    364.43922052345687, 
    222.15118532009322, 
    88.56214528333032, 
    881.4722741880154, 
    196.5767668118658, 
    310.17513018463245, 
    719.2022437373903, 
    293.87185882740636, 
    544.8766053582586, 
    1609.6704197021304, 
    253.57509943673227, 
    207.3902510555587, 
    289.18795433002254, 
    265.95029739805636, 
    15.402594850840952, 
    473.03725482386255, 
    17.55482081718124, 
    386.1034762108376, 
    1731.8348297527582, 
    147.19928617168046, 
    456.6742594747476, 
    818.3809282535805, 
    171.18344082757923, 
    1.9741602967824547, 
    193.6325782143977, 
    131.875579542767, 
    646.6248240940629, 
    0.8827125998732448, 
    286.74016246307394, 
    270.52092318657014, 
    277.79309246606834, 
    182.61525978236958, 
    153.0191331168845, 
    334.9780798240635, 
    33.794100740162314, 
    490.5049359781523, 
    201.01672491309716, 
    858.1869824638361, 
    430.90394034873384, 
    249.47504121199228, 
    27.233069016712296, 
    231.10264009634335, 
    171.6782602143438, 
    279.6211045600366, 
    326.3502813322277, 
    285.42003299866474, 
    693.3970352007365, 
    0.0, 
    250.15566682588272, 
    293.5902984460678, 
    860.7740090084391, 
    99.4391361962976, 
    655.2874911804032, 
    695.1208115165292, 
    299.2855682999012, 
    3.841131117937794, 
    269.10906649060286, 
    432.36337531417837, 
    1621.5448122348976, 
    365.3637928246902, 
    238.72216905664203, 
    1586.8464368043788, 
    30.64323966200759, 
    209.22978315223355, 
    110.77409602721548, 
    599.2542890673011, 
    184.75311516768522, 
    292.5594210610051, 
    91.71199733533675, 
    282.3913892891136, 
    78.10616926009124, 
    305.83994391058155, 
    81.46174817218545, 
    531.1756501978607, 
    67.71980512885034, 
    361.269192209703, 
    558.3721947709316, 
    210.39135200540423, 
    5.924250614516503, 
    270.50373591174235, 
    67.527558823404, 
    447.2946729826535, 
    943.2152268192364, 
    64.9387520693991, 
    301.96826976759326, 
    41.589346479208736, 
    286.4093783855378, 
    504.7122426502596, 
    629.334831512606, 
    184.01436434423488, 
    234.73889664906798, 
    286.0957710505374, 
    460.67260232748896, 
    255.7476888765102, 
    292.7961245921179, 
    293.5416992191514, 
    274.41068312363177, 
    166.44266256417674, 
    275.1650716896995, 
    206.94509734530286, 
    51.06446510455046, 
    249.60331609664405, 
    149.28140447570308, 
    1516.262954278192, 
    389.74040019422023, 
    201.3533254246931, 
    523.6021198273239, 
    249.12454747646748, 
    118.146451193054, 
    96.42209170366154, 
    40.12323535695449, 
    99.87952502488197, 
    77.01755408100243, 
    440.5939897351505, 
    384.4284062099367, 
    350.6007492122231, 
    214.4433452469109, 
    49.027565949743746, 
    283.54034045429563, 
    324.62220397311944, 
    22.956740592307963, 
    313.3611129694923, 
    2.6802974868652343, 
    8.217516807572359, 
    172.53238786233752, 
    744.8964095400952, 
    204.45033411123845, 
    322.7089459791701, 
    1518.3057288386135, 
    352.05232272427435, 
    68.54825932511432, 
    88.60618810829621, 
    245.20613498000614, 
    348.75606500812717, 
    37.795155664850206, 
    103.26129843934905, 
    261.9668346750889, 
    1315.8501952603178, 
    102.85862405884284, 
    1869.0920191842172, 
    110.01554405756683, 
    57.654097791967786, 
    411.81945417653685, 
    452.0432120271929, 
    2.117793071591705, 
    249.29416501316672, 
    294.6711550877666, 
    1419.0776391071615, 
    784.8007089459879, 
    178.17715418633537, 
    156.6390305415974, 
    94.5962929488856, 
    350.00331517349946, 
    613.8894081066762, 
    113.08653319719343, 
    232.3392844860086, 
    381.9281706043951, 
    877.3872856101973, 
    348.69435762211265, 
    0.8859682634923481, 
    1.8649109199298852, 
    265.2703548130158, 
    355.047826557426, 
    76.5787149570274, 
    386.23079397200576, 
    49.172470056926514, 
    321.8634712467702, 
    228.0615359633658, 
    1223.0503458857766, 
    1212.2922630104417, 
    317.83869594136786, 
    1197.2771836942482, 
    77.22574117898594, 
    406.4143149284427, 
    79.10250408004951, 
    190.69443204420602, 
    348.31929284584515, 
    275.4071862505895, 
    1481.5945433216148, 
    322.9233801794868, 
    572.6776610709859, 
    318.2165012467838, 
    436.23031547914, 
    214.7527248845972, 
    599.2321778009209, 
    887.8885340617729, 
    229.5297819353618, 
    219.46883066249254, 
    1988.5663839694298, 
    265.8318237372558, 
    353.4333369534917, 
    47.51845793064617, 
    423.04893400690713, 
    247.50404043955285, 
    274.75409738632106, 
    357.2043688507107, 
    422.8481638613715, 
    178.00356967893956, 
    7.243591507922946, 
    124.56700978063952, 
    173.6604846188741, 
    224.39492019209374, 
    54.775037178030004, 
    327.1928581897293, 
    108.03084792231942, 
    37.479742911961736, 
    269.5896490209512, 
    175.11572405546013, 
    196.93245176148238, 
    965.7567535350651, 
    103.00935895083266, 
    84.66144150045531, 
    191.16192476588068, 
    320.58843879936154, 
    169.33504509962833, 
    160.87868649899224, 
    136.32435367068234, 
    186.65991641180005, 
    2.859975386960021, 
    494.32866327172195, 
    316.3488121397552, 
    312.930651280945, 
    20.7451098798423, 
    320.9511818912569, 
    369.8688086210632, 
    1274.574503099615, 
    29.273146178257942, 
    106.56924405177388, 
    273.4454176762067, 
    700.4929242125074, 
    369.5512338863824, 
    82.52234221840811, 
    360.7636202163618, 
    116.74100696403066, 
    102.69953393450885, 
    1846.8289526270792, 
    1585.4399185937157, 
    126.06174365564362, 
    178.03563873764975, 
    266.64160407966574, 
    15.599494852264101, 
    908.5774136438095, 
    759.3148616795603, 
    28.478459349370766, 
    409.25635209111306, 
    263.87080407531124, 
    272.01691838983845, 
    857.7654040507243, 
    421.00449165214496, 
    55.48011248392662, 
    11.663088629049813, 
    298.1314328170332, 
    361.60337413007016, 
    218.48477262996076, 
    1837.7551982616058, 
    266.05209849882056, 
    413.26152235800527, 
    442.0964544453861, 
    2.9343175866050974, 
    108.37903603783778, 
    335.4065611870157, 
    17.549055357389705, 
    76.64157336198326, 
    5.068969809358903, 
    297.920816850614, 
    0.0, 
    58.575578488584085, 
    51.46169843235321, 
    123.58835835324805, 
    212.41230284562099, 
    206.12918120342755, 
    381.2191870823254, 
    398.5759726000075, 
    270.12789133843916, 
    392.233584925498, 
    0.0, 
    307.1952914014273, 
    503.5055457363035, 
    388.8609885399652, 
    159.64356683057164, 
    337.16287863273095, 
    57.041443557070835, 
    294.48517576830056, 
    241.2743758975135, 
    269.5429878175131, 
    208.45801281042475, 
    234.78657377740285, 
    885.031603099855, 
    21.313433177049752, 
    234.6429745694995, 
    272.8304693416723, 
    240.5909150276937, 
    90.01977990642673, 
    559.0549690765924, 
    391.18863229158427, 
    151.2651700507979, 
    816.2352407130986, 
    255.8542799321569, 
    163.09532282943678, 
    60.80796019575055, 
    432.5175748114032, 
    7.885126789852153, 
    1298.256511972908, 
    48.60673018705105, 
    103.59402913222792, 
    319.92938585596943, 
    61.71749480009116, 
    0.9613737460539916, 
    39.21430562249426, 
    257.9387765129631, 
    31.006702251759204, 
    245.83019708486864, 
    82.72159231332543, 
    285.85514861946996, 
    103.60963764813584, 
    231.2535435633321, 
    5.856529977530845, 
    336.0413971206457, 
    357.7534973579977, 
    127.67022813009581, 
    165.85520610510486, 
    15.347095716768163, 
    665.9032821499346, 
    15.133951622129063, 
    1024.7198968088971, 
    130.12432966375093, 
    167.80273367023892, 
    31.521646978014306, 
    751.8573782212753, 
    278.81930853262685, 
    84.8872010184008, 
    314.7831352077559, 
    695.4754912831422, 
    203.2905011678008, 
    357.2968475122493, 
    287.4041745324662, 
    328.3991680531641, 
    28.3918417466205, 
    691.427964318825, 
    379.1771167901033, 
    302.36612947839296, 
    351.6072942035126, 
    2359.867279847503, 
    313.868932925531, 
    246.3159057308726, 
    166.3659796515594, 
    362.12185870975503, 
    392.66312397608607, 
    343.9632461613175, 
    377.4500208642226, 
    6.7001320808075775, 
    244.73194014457937, 
    112.67942805748683, 
    800.5737633892152, 
    395.07234879530506, 
    241.4853067261782, 
    257.6954429202501, 
    600.2168740577409, 
    255.09343718661162, 
    11.375431568461252, 
    210.27441224656684, 
    526.4117865419792, 
    41.241620705471696, 
    49.71567331996657, 
    14.721503030826259, 
    41.73400307378329, 
    313.55777126495144, 
    10.450798562622808, 
    154.5486974948581, 
    199.4932791619663, 
    208.5784383500499, 
    62.41420518713656, 
    458.038203315532, 
    981.1064318153599, 
    28.610014188895104, 
    243.74346197733482, 
    69.50394065584884, 
    100.48243715028327, 
    418.32279251881715, 
    236.15516356603607, 
    47.8296942934076, 
    326.6169233453691, 
    329.17261268056706, 
    16.905250589781655, 
    165.29415731246104, 
    587.8015590227957, 
    258.46136190865406, 
    210.713852218492, 
    119.68047821915187, 
    179.36948279874304, 
    415.6347322690611, 
    163.7943656440105, 
    174.05602940535493, 
    13.220850898056172, 
    124.2005457235572, 
    186.73444431304665, 
    289.55356741303933, 
    197.1831535184483, 
    322.06995850325006, 
    142.2887290831794, 
    8.3866967741189, 
    424.99776364315, 
    21.673357347000167, 
    296.38822081737203, 
    15.311669862648236, 
    234.61512534384622, 
    356.81470553179093, 
    10.06114183348817, 
    62.86823418097215, 
    148.1918737350759, 
    460.60072390799115, 
    319.17681115025493, 
    302.8591211904349, 
    290.11147384025145, 
    326.62151751642807, 
    50.64681814183322, 
    366.31866347622906, 
    184.80122760093795, 
    250.94402889421454, 
    281.6616249124419, 
    330.82621481216967, 
    5.905651911708023, 
    367.9718254298375, 
    296.24446786449204, 
    259.0672310237047, 
    430.7753036519467, 
    10.24231335529225, 
    259.3072144064208, 
    318.8800809461184, 
    189.5811637498993, 
    30.12374493690133, 
    26.793659369264578, 
    163.07866111328818, 
    1290.1678669215253, 
    1418.3782665836447, 
    407.3006472303192, 
    379.79718508506284, 
    261.93489560850236, 
    508.03141773686525, 
    152.0100367028149, 
    99.29448483918998, 
    330.8231315276649, 
    7.219786189239403, 
    20.180849907930888, 
    73.3530168772105, 
    4.692325206591425, 
    235.7119128453491, 
    189.41464089442908, 
    320.014256875236, 
    0.9740839630230961, 
    1054.6031094215236, 
    467.2281217116697, 
    99.3575243105805, 
    16.505180396955854, 
    33.464011741538535, 
    37.28929461692844, 
    242.23716871300928, 
    733.441537118419, 
    461.4784211550992, 
    375.58715979497725, 
    228.9819033499355, 
    429.424414414044, 
    326.5357224902658, 
    11.970784933463625, 
    46.607331161582444, 
    105.72071299548811, 
    327.21101900407035, 
    336.1706484906821, 
    535.1498351762947, 
    391.08955509585405, 
    6.0083114895538206, 
    645.3683954642272, 
    22.655149554428625, 
    296.33951887082804, 
    271.3111759380285, 
    186.74039962018364, 
    361.1343181853645, 
    316.5792703638813, 
    444.3620316025038, 
    313.08397101987913, 
    453.15353711312923, 
    271.6622715490384, 
    321.7596428613176, 
    333.839062024867, 
    218.8847380073421, 
    339.1638902844658, 
    763.0513787797227, 
    58.83762556225646, 
    224.3015959689247, 
    151.9901296496007, 
    261.5302511413424, 
    497.84294697849424, 
    909.3859080270114, 
    217.96216906425994, 
    116.51803074018098, 
    3.0459963968988033, 
    303.43288300936285, 
    897.0650903531509, 
    31.757140105625233, 
    429.0248389150391, 
    107.68146010711716, 
    325.94726906220495, 
    649.4992049066517, 
    567.8445992323387, 
    4.087755660920129, 
    267.3913288237312, 
    242.71235290365314, 
    579.506259153861, 
    182.6261091787025, 
    297.3306642498873, 
    183.0356422558371, 
    271.1995629654274, 
    220.9201384045716, 
    422.9504250051977, 
    488.1138190525718, 
    116.58523908080603, 
    109.53863073397275, 
    202.40120406178133, 
    168.484133994166, 
    263.83561752155333, 
    277.9503078402895, 
    86.8713397421539, 
    38.69425252946806, 
    1205.497083646973, 
    80.10510739558015, 
    1656.714626320265, 
    200.3569721370473, 
    569.5438229514257, 
    184.75024974359332, 
    407.21643243471476, 
    17.793085348290738, 
    169.21471653986077, 
    127.60852369982784, 
    285.62558534038993, 
    194.48549655787352, 
    448.03541600639545, 
    86.33412067740498, 
    204.1419531629894, 
    556.4433006316268, 
    867.9389289992101, 
    328.4355884310254, 
    173.62684724700108, 
    373.1173034295371, 
    157.00459278842297, 
    355.25596597061093, 
    131.2201305385105, 
    69.22260675507529, 
    760.2269223913038, 
    164.51081175462616, 
    272.01447966326117, 
    541.9470661937814, 
    327.24265525437687, 
    205.70238003754196, 
    220.97851344410606, 
    347.17506060682246, 
    131.72362330420387, 
    1603.5082246354675, 
    178.05476864594195, 
    292.7666648942453, 
    226.3372993024706, 
    43.02753944505527, 
    319.32920739439953, 
    323.5089400515996, 
    217.07609167125327, 
    178.60225011049448, 
    85.41547154160244, 
    318.34525601548233, 
    475.72182326582964, 
    276.21380870601695, 
    306.7462282957629, 
    256.0346912945457, 
    13.214965418062969, 
    394.91744302003065, 
    504.93741001610726, 
    945.2955712815769, 
    122.23898300955595, 
    168.42018771330444, 
    336.2971465067687, 
    362.2528593093729, 
    263.68169237655485, 
    212.56350350329896, 
    78.52911697995651, 
    1363.413761323821, 
    264.69082910740224, 
    222.83930278616947, 
    422.0510346515241, 
    168.34844688976972, 
    41.89685662313507, 
    132.94627826672212, 
    154.71785855626047, 
    301.234432034708, 
    136.1492556922677, 
    317.71012667094897, 
    231.43517390545864, 
    585.8373193016357, 
    3.143875013892291, 
    102.82590954529934, 
    392.26255648950996, 
    37.26076694283548, 
    178.5408796537912, 
    318.5041858467097, 
    396.66382063992637, 
    359.272354768152, 
    217.04899149177675, 
    409.76578328591876, 
    211.18775251210852, 
    358.0965849443663, 
    229.408144407403, 
    471.5059921819886, 
    230.06691514184905, 
    188.01923466199185, 
    218.07499046053485, 
    220.14866392951177, 
    213.88169380828325, 
    191.92082919451965, 
    292.23043189993524, 
    611.8019964411283, 
    10.468494685424078, 
    359.684248731846, 
    138.64232828771392, 
    320.69260178624114, 
    852.7828859918766, 
    435.86602840207075, 
    38.15315653393961, 
    356.6615008916419, 
    352.1280179536548, 
    131.54541812155088, 
    178.98580506805308, 
    408.068994450057, 
    24.57013426897572, 
    388.4536804110934, 
    314.0045551092999, 
    178.7541927828383, 
    145.41177774985718, 
    379.1952490166802, 
    100.14763629892282, 
    18.35358385314627, 
    280.55616772835083, 
    178.0795483683309, 
    418.9777524855221, 
    949.5612763963629, 
    70.6299581979124, 
    244.49191848797534, 
    880.6630667724347, 
    295.63927832263147, 
    339.00037601680674, 
    69.31425233762084, 
    68.33744896367523, 
    21.689682831558134, 
    80.60262775294625, 
    78.86350274262848, 
    1341.7755547332047, 
    471.93127395240185, 
    59.64229831238133, 
    504.4269710405645, 
    139.06120208948897, 
    302.4891016557163, 
    415.02301834538935, 
    518.7901835187771, 
    594.7760989134783, 
    21.66445393582947, 
    291.27172493888264, 
    149.93705796645304, 
    3.149599473711393, 
    446.9133365585536, 
    298.92520864533145, 
    345.7187179718959, 
    160.24982212490914, 
    4.095148100402219, 
    475.90794777839716, 
    952.2290635369005, 
    264.25696571891956, 
    458.8185411129709, 
    289.7447188112132, 
    1075.9689080836872, 
    17.527618572208148, 
    30.583124384281305, 
    143.54336652017497, 
    229.75658125173214, 
    166.0885579450626, 
    81.28583299729232, 
    2.9120836461167405, 
    490.82378480928986, 
    261.140991061057, 
    159.7801219837406, 
    43.1147769018322, 
    391.4224748447283, 
    326.0844261771331, 
    270.5110809993831, 
    348.2295919299606, 
    251.54442038869854, 
    262.6294004379719, 
    531.3563357154835, 
    262.7306866010465, 
    140.96125151855531, 
    196.56551464608313, 
    745.5463828454359, 
    124.07808854426408, 
    157.25453829574454, 
    263.42407361277316, 
    298.14462342666405, 
    471.04722701874, 
    186.96400083886172, 
    190.2573720541895, 
    154.28676388926684, 
    39.22638319523448, 
    330.5132541924344, 
    608.6724157764235, 
    65.2022494706195, 
    269.4966608580498, 
    25.864697169152212, 
    485.06139647333873, 
    250.05577663284424, 
    667.9251444291607, 
    302.1309718143625, 
    291.84669028183254, 
    737.5217883553184, 
    317.4137825206175, 
    686.7912161075582, 
    9.24564814013466, 
    1153.3735038414575, 
    556.583044912954, 
    270.2706407990637, 
    214.0555159887309, 
    189.09508148210494, 
    77.78441655832107, 
    4.931039068484128, 
    646.8654594836577, 
    2.95977473538973, 
    42.053979948199135, 
    380.31210967098656, 
    601.5706426614314, 
    298.53170436872324
  ]
}
